mkdocsexport/__init__.py
mkdocsexport/plugin.py
mkdocsexport/version.py
mkdocsexport/templates/export.json.template
mkdocsexport-1.0.1.dist-info/LICENSE.md
mkdocsexport-1.0.1.dist-info/METADATA
mkdocsexport-1.0.1.dist-info/WHEEL
mkdocsexport-1.0.1.dist-info/entry_points.txt
mkdocsexport-1.0.1.dist-info/top_level.txt
mkdocsexport-1.0.1.dist-info/RECORD
