Metadata-Version: 2.1
Name: mkdocsexport
Version: 1.0.1
Summary: Export documents to a single file. It makes use of a template so the format can be whatever you want (JSON, CSV, One big HTML file, what-ever)
Home-page: https://github.com/philips-labs/MkdocsExportPlugin
Author: Simon de Turck
Author-email: simon.de.turck@philips.com
License: MIT
Keywords: mkdocs python markdown export
Platform: UNKNOWN
Classifier: Programming Language :: Python :: 3
Classifier: License :: OSI Approved :: MIT License
Classifier: Operating System :: OS Independent
Requires-Python: >=3.6
License-File: LICENSE.md
Requires-Dist: mkdocs (>=1.1)
Requires-Dist: jinja2
